universal_upsa-0.1.3.dist-info/licenses/LICENSE
upsa/__init__.py
upsa/upsa.py
universal_upsa-0.1.3.dist-info/METADATA
universal_upsa-0.1.3.dist-info/WHEEL
universal_upsa-0.1.3.dist-info/top_level.txt
universal_upsa-0.1.3.dist-info/RECORD
