Metadata-Version: 2.4
Name: universal-upsa
Version: 0.1.3
Summary: Unbiased Portfolio Shrinkage Approach (UPSA) with LOO or k-fold CV
Author-email: Mo Pourmohammadi <mo.pourmohammadi@yale.edu>
License: MIT
License-File: LICENSE
Requires-Dist: numpy>=1.20
Requires-Dist: scikit-learn>=1.0
Requires-Dist: cvxopt>=1.3
Dynamic: license-file
